unfollowery/__cfg.py
unfollowery/__init__.py
unfollowery/__utils.py
unfollowery/crawler.py
unfollowery-2.2.dist-info/LICENSE
unfollowery-2.2.dist-info/METADATA
unfollowery-2.2.dist-info/WHEEL
unfollowery-2.2.dist-info/top_level.txt
unfollowery-2.2.dist-info/RECORD
