Metadata-Version: 2.1
Name: unfollowery
Version: 2.2
Summary: For generating Instagram followers/unfollowers of the user in a list & file (without using Instagram API)
Home-page: https://github.com/lukasanukvari/unfollowery
Author: Luka Sosiashvili
Author-email: luksosiashvili@gmail.com
License: UNKNOWN
Platform: UNKNOWN
Classifier: Programming Language :: Python :: 3
Classifier: License :: OSI Approved :: MIT License
Classifier: Operating System :: OS Independent
Requires-Python: >=3.8
License-File: LICENSE
Requires-Dist: selenium
Requires-Dist: pandas
